b3dkit/__init__.py
b3dkit/antichamfer.py
b3dkit/ball_socket.py
b3dkit/basic_shapes.py
b3dkit/bolt_fittings.py
b3dkit/click_fit.py
b3dkit/dovetail.py
b3dkit/hexwall.py
b3dkit/high_top_slide_box.py
b3dkit/point.py
b3dkit/slide_box.py
b3dkit/twist_snap.py
b3dkit-0.1.2.dist-info/METADATA
b3dkit-0.1.2.dist-info/WHEEL
b3dkit-0.1.2.dist-info/licenses/LICENSE
b3dkit-0.1.2.dist-info/RECORD
