Metadata-Version: 2.4
Name: b3dkit
Version: 0.1.2
Summary: build123d libraries and utilities
Project-URL: Homepage, https://github.com/x0pherl/b3dkit
Project-URL: Issues, https://github.com/x0pherl/b3dkit/issues
Project-URL: Documentation, https://b3dkit.readthedocs.org
Author: x0pherl
License-File: LICENSE
Classifier: License :: OSI Approved :: MIT License
Classifier: Operating System :: OS Independent
Classifier: Programming Language :: Python :: 3
Requires-Python: >=3.8
Requires-Dist: build123d>=0.0.1
Requires-Dist: ocp-vscode
Provides-Extra: dev
Requires-Dist: pytest; extra == 'dev'
Requires-Dist: pytest-cov; extra == 'dev'
Provides-Extra: docs
Requires-Dist: markdown-include; extra == 'docs'
Requires-Dist: mkdocs; extra == 'docs'
Requires-Dist: mkdocs-material; extra == 'docs'
Provides-Extra: maintain
Requires-Dist: build; extra == 'maintain'
Requires-Dist: hatch-vcs; extra == 'maintain'
Requires-Dist: hatchling; extra == 'maintain'
Requires-Dist: twine; extra == 'maintain'
